CHANGELOG.md
starlite_multipart/__init__.py
starlite_multipart/constants.py
starlite_multipart/datastructures.py
starlite_multipart/decoder.py
starlite_multipart/encoder.py
starlite_multipart/events.py
starlite_multipart/parser.py
starlite_multipart/py.typed
starlite_multipart/utils.py
starlite_multipart-1.2.0.dist-info/LICENSE
starlite_multipart-1.2.0.dist-info/WHEEL
starlite_multipart-1.2.0.dist-info/METADATA
starlite_multipart-1.2.0.dist-info/RECORD
